generative_redfoot/__init__.py
generative_redfoot/cli.py
generative_redfoot/object_pdl_model.py
generative_redfoot/utils.py
generative_redfoot/extensions/__init__.py
generative_redfoot/extensions/toolio.py
generative_redfoot/extensions/wordloom.py
generative_redfoot-0.1.1.dist-info/licenses/LICENSE
generative_redfoot-0.1.1.dist-info/METADATA
generative_redfoot-0.1.1.dist-info/WHEEL
generative_redfoot-0.1.1.dist-info/entry_points.txt
generative_redfoot-0.1.1.dist-info/top_level.txt
generative_redfoot-0.1.1.dist-info/RECORD
