Metadata-Version: 2.4
Name: generative_redfoot
Version: 0.1.1
Summary: A generative, conversational workflow and multi-agent system using PDL and mlx
Author-email: Chimezie Ogbuji <chimezie@gmail.com>
License: MIT License
Project-URL: Homepage, https://github.com/chimezie/generative_redfoot
Project-URL: Repository, https://github.com/chimezie/generative_redfoot
Classifier: Development Status :: 4 - Beta
Classifier: Programming Language :: Python
Classifier: Programming Language :: Python :: 3.11
Classifier: Programming Language :: Python :: Implementation :: PyPy
Requires-Python: >=3.10
License-File: LICENSE
Requires-Dist: pyaml
Requires-Dist: click
Requires-Dist: tqdm
Requires-Dist: ogbujipt
Requires-Dist: mlx>=0.26.3
Requires-Dist: mlx-lm>=0.26.0
Requires-Dist: pytest
Requires-Dist: transformers
Provides-Extra: gemma-aps
Requires-Dist: nltk; extra == "gemma-aps"
Dynamic: license-file
